crypto_address_validator/__init__.py
crypto_address_validator/validators/__init__.py
crypto_address_validator/validators/aion_validator.py
crypto_address_validator/validators/atom_validator.py
crypto_address_validator/validators/bnb_validator.py
crypto_address_validator/validators/crypto/bech32m.py
crypto_address_validator/validators/default_validator.py
crypto_address_validator/validators/eos_validator.py
crypto_address_validator/validators/iost_validator.py
crypto_address_validator/validators/miota_validator.py
crypto_address_validator-0.5.0.dist-info/LICENSE
crypto_address_validator-0.5.0.dist-info/WHEEL
crypto_address_validator-0.5.0.dist-info/METADATA
crypto_address_validator-0.5.0.dist-info/RECORD
