Metadata-Version: 2.1
Name: crypto-address-validator
Version: 0.5.0
Summary: Simple validation tool for Bitcoin and other altcoin addresses.
Author: null-po1nter
Author-email: me.nullptr@gmail.com
Requires-Python: >=3.8,<4.0
Classifier: Programming Language :: Python :: 3
Classifier: Programming Language :: Python :: 3.10
Classifier: Programming Language :: Python :: 3.8
Classifier: Programming Language :: Python :: 3.9
Requires-Dist: base58 (>=2.1.1,<3.0.0)
Requires-Dist: bech32 (>=1.2.0,<2.0.0)
